Metadata-Version: 1.1
Name: MarkovTextGeneration
Version: 0.1.3
Summary: Generating hallucinated text with Markov Chains
Home-page: https://github.com/Sam-Nielsen-Dot/MarkovTextGeneration
Author: Sam Nielsen
Author-email: lenssimane@gmail.com
License: MIT
Platform: UNKNOWN
Classifier: Development Status :: 1 - Planning
Classifier: Environment :: Win32 (MS Windows)
Classifier: License :: OSI Approved :: MIT License
Classifier: Natural Language :: English
Classifier: Programming Language :: Python :: 2
Classifier: Programming Language :: Python :: 2.7
Classifier: Programming Language :: Python :: 3
Classifier: Programming Language :: Python :: 3.4
Classifier: Programming Language :: Python :: 3.5
